snapcat/__init__.py
snapcat/cat_utils.py
snapcat/config.py
snapcat/export_cmd/__init__.py
snapcat/shared.py
snapcat/show_cmd/__init__.py
snapcat/sync_cmd/__init__.py
snapcat/sync_cmd/sync.py
snapcat-0.1.3.dist-info/LICENSE
snapcat-0.1.3.dist-info/METADATA
snapcat-0.1.3.dist-info/WHEEL
snapcat-0.1.3.dist-info/entry_points.txt
snapcat-0.1.3.dist-info/RECORD
