Metadata-Version: 2.1
Name: snapcat
Version: 0.1.3
Summary: snapcat is a Python command-line tool that helps monitor CATs (Chia Asset Tokens) on Chia Blockchain.
Author: Dexie Contributors
Author-email: pypi@dexie.space
Requires-Python: >=3.12,<4.0
Classifier: Programming Language :: Python :: 3
Classifier: Programming Language :: Python :: 3.12
Requires-Dist: asyncio (>=3.4.3,<4.0.0)
Requires-Dist: python-dotenv (>=1.0.1,<2.0.0)
Requires-Dist: rich-click (>=1.8.0,<2.0.0)
